[{"categories":["travel"],"contents":"Lorem ipsum dolor sit amet, consectetur adipiscing elit. sed do eiusmod tempor incididunt ut labore et dolore magna aliqua. Ut enim ad minim veniam, quis nostrud exercitation ullamco laboris nisi ut aliquip ex ea commodo consequat. Duis aute irure dolor in reprehenderit in voluptate velit esse cillum dolore eu fugiat nulla pariatur. Excepteur sint occaecat cupidatat non proident, sunt in culpa qui officia deserunt mollit anim id est laborum.\nLorem ipsum dolor sit amet, consectetur adipiscing elit. sed do eiusmod tempor incididunt ut labore et dolore magna aliqua. Ut enim ad minim veniam, quis nostrud exercitation ullamco laboris nisi ut aliquip ex ea commodo consequat. Duis aute irure dolor in reprehenderit in voluptate velit esse cillum dolore eu fugiat nulla pariatur. Excepteur sint occaecat cupidatat non proident, sunt in culpa qui officia deserunt mollit anim id est laborum.Lorem ipsum dolor sit amet, consectetur adipiscing elit. sed do eiusmod tempor incididunt ut labore et dolore magna aliqua. Ut enim ad minim veniam, quis nostrud exercitation ullamco laboris nisi ut aliquip ex ea commodo consequat. Duis aute irure dolor in reprehenderit in voluptate velit esse cillum dolore eu fugiat nulla pariatur. Excepteur sint occaecat cupidatat non proident, sunt in culpa qui officia deserunt mollit anim id est laborum.\nLorem ipsum dolor sit amet, consetetur sadipscing elitr, sed diam nonumy eirmod tempor invidunt ut labore et dolore magna aliquyam erat, sed diam voluptua. At vero eos et accusam et justo duo dolores et ea rebum. Stet clita kasd gubergren, no sea takimata sanctus est Lorem ipsum dolor sit amet. Lorem ipsum dolor sit amet, consetetur sadipscing elitr,\nLorem ipsum dolor sit amet, consectetur adipiscing elit. sed do eiusmod tempor incididunt ut labore et dolore magna aliqua. Ut enim ad minim veniam, quis nostrud exercitation ullamco laboris nisi ut aliquip ex ea commodo consequat. Duis aute irure dolor in reprehenderit in voluptate velit esse cillum dolore eu fugiat nulla pariatur. Excepteur sint occaecat cupidatat non proident, sunt in culpa qui officia deserunt mollit anim id est laborum.Lorem ipsum dolor sit amet, consectetur adipiscing elit. sed do eiusmod tempor incididunt ut labore et dolore magna aliqua. Ut enim ad minim veniam, quis nostrud exercitation ullamco laboris nisi ut aliquip ex ea commodo consequat. Duis aute irure dolor in reprehenderit in voluptate velit esse cillum dolore eu fugiat nulla pariatur. Excepteur sint occaecat cupidatat non proident, sunt in culpa qui officia deserunt mollit anim id est laborum.\nLorem ipsum dolor sit amet, consectetur adipiscing elit. sed do eiusmod tempor incididunt ut labore et dolore magna aliqua. Ut enim ad minim veniam, quis nostrud exercitation ullamco laboris nisi ut aliquip ex ea commodo consequat. Duis aute irure dolor in reprehenderit in voluptate velit esse cillum dolore eu fugiat nulla pariatur. Excepteur sint occaecat cupidatat non proident, sunt in culpa qui officia deserunt mollit anim id est laborum.Lorem ipsum dolor sit amet, consectetur adipiscing elit. sed do eiusmod tempor incididunt ut labore et dolore magna aliqua. Ut enim ad minim veniam, quis nostrud exercitation ullamco laboris nisi ut aliquip ex ea commodo consequat. Duis aute irure dolor in reprehenderit in voluptate velit esse cillum dolore eu fugiat nulla pariatur. Excepteur sint occaecat cupidatat non proident, sunt in culpa qui officia deserunt mollit anim id est laborum.\n","date":"October 1, 2021","image":"\n\n\n\n\n\n\n\n\n\n\n\n\n\n\n\n\n\n\n\n\n\n\n\n\n\n\n\n\n  \n\n\n\n\n\n  \n\n  \n  \n    \n      \n    \n\n\n    \n    \n\n\n    \n    \n      \n      \n    \n    \n    \n\n\n    \n    \n      \n      \n        \n\n        \n        \n        \n        \n        \n        \n        \n\n\n        \n        \n\n\n        \u003cpicture\u003e\n          \u003csource\n            \n              srcset=\"/images/blog/02_hu_5a0cc429c5b09cbb.webp\"\n            \n            media=\"(max-width: 575px)\" /\u003e\n          \u003csource\n            \n              srcset=\"/images/blog/02_hu_94e26dabc52d5b1a.webp\"\n            \n            media=\"(max-width: 767px)\" /\u003e\n          \u003csource\n            \n              srcset=\"/images/blog/02_hu_191af9772de76ed9.webp\"\n            \n            media=\"(max-width: 991px)\" /\u003e\n          \u003csource\n            \n              srcset=\"/images/blog/02_hu_133250fe56b5983f.webp\"\n             /\u003e\n          \u003cimg\n            \n              loading=\"lazy\" decoding=\"async\"\n              src=\"/images/blog/02_hu_e05ff2961349605d.jpg\"\n            class=\"  img\"\n            alt=\"\"\n            width=\"1200\"\n            height=\"800\" /\u003e\n        \u003c/picture\u003e\n      \n      \n    \n    \n  \n\n\n  \n\n","permalink":"/blog/post-2/","title":"Do what you can, with you have, where you are"},{"categories":["hobby"],"contents":"Lorem ipsum dolor sit amet, consectetur adipiscing elit. sed do eiusmod tempor incididunt ut labore et dolore magna aliqua. Ut enim ad minim veniam, quis nostrud exercitation ullamco laboris nisi ut aliquip ex ea commodo consequat. Duis aute irure dolor in reprehenderit in voluptate velit esse cillum dolore eu fugiat nulla pariatur. Excepteur sint occaecat cupidatat non proident, sunt in culpa qui officia deserunt mollit anim id est laborum.\nLorem ipsum dolor sit amet, consectetur adipiscing elit. sed do eiusmod tempor incididunt ut labore et dolore magna aliqua. Ut enim ad minim veniam, quis nostrud exercitation ullamco laboris nisi ut aliquip ex ea commodo consequat. Duis aute irure dolor in reprehenderit in voluptate velit esse cillum dolore eu fugiat nulla pariatur. Excepteur sint occaecat cupidatat non proident, sunt in culpa qui officia deserunt mollit anim id est laborum.Lorem ipsum dolor sit amet, consectetur adipiscing elit. sed do eiusmod tempor incididunt ut labore et dolore magna aliqua. Ut enim ad minim veniam, quis nostrud exercitation ullamco laboris nisi ut aliquip ex ea commodo consequat. Duis aute irure dolor in reprehenderit in voluptate velit esse cillum dolore eu fugiat nulla pariatur. Excepteur sint occaecat cupidatat non proident, sunt in culpa qui officia deserunt mollit anim id est laborum.\nLorem ipsum dolor sit amet, consetetur sadipscing elitr, sed diam nonumy eirmod tempor invidunt ut labore et dolore magna aliquyam erat, sed diam voluptua. At vero eos et accusam et justo duo dolores et ea rebum. Stet clita kasd gubergren, no sea takimata sanctus est Lorem ipsum dolor sit amet. Lorem ipsum dolor sit amet, consetetur sadipscing elitr,\nLorem ipsum dolor sit amet, consectetur adipiscing elit. sed do eiusmod tempor incididunt ut labore et dolore magna aliqua. Ut enim ad minim veniam, quis nostrud exercitation ullamco laboris nisi ut aliquip ex ea commodo consequat. Duis aute irure dolor in reprehenderit in voluptate velit esse cillum dolore eu fugiat nulla pariatur. Excepteur sint occaecat cupidatat non proident, sunt in culpa qui officia deserunt mollit anim id est laborum.Lorem ipsum dolor sit amet, consectetur adipiscing elit. sed do eiusmod tempor incididunt ut labore et dolore magna aliqua. Ut enim ad minim veniam, quis nostrud exercitation ullamco laboris nisi ut aliquip ex ea commodo consequat. Duis aute irure dolor in reprehenderit in voluptate velit esse cillum dolore eu fugiat nulla pariatur. Excepteur sint occaecat cupidatat non proident, sunt in culpa qui officia deserunt mollit anim id est laborum.\nLorem ipsum dolor sit amet, consectetur adipiscing elit. sed do eiusmod tempor incididunt ut labore et dolore magna aliqua. Ut enim ad minim veniam, quis nostrud exercitation ullamco laboris nisi ut aliquip ex ea commodo consequat. Duis aute irure dolor in reprehenderit in voluptate velit esse cillum dolore eu fugiat nulla pariatur. Excepteur sint occaecat cupidatat non proident, sunt in culpa qui officia deserunt mollit anim id est laborum.Lorem ipsum dolor sit amet, consectetur adipiscing elit. sed do eiusmod tempor incididunt ut labore et dolore magna aliqua. Ut enim ad minim veniam, quis nostrud exercitation ullamco laboris nisi ut aliquip ex ea commodo consequat. Duis aute irure dolor in reprehenderit in voluptate velit esse cillum dolore eu fugiat nulla pariatur. Excepteur sint occaecat cupidatat non proident, sunt in culpa qui officia deserunt mollit anim id est laborum.\n","date":"October 1, 2021","image":"\n\n\n\n\n\n\n\n\n\n\n\n\n\n\n\n\n\n\n\n\n\n\n\n\n\n\n\n\n  \n\n\n\n\n\n  \n\n  \n  \n    \n      \n    \n\n\n    \n    \n\n\n    \n    \n      \n      \n    \n    \n    \n\n\n    \n    \n      \n      \n        \n\n        \n        \n        \n        \n        \n        \n        \n\n\n        \n        \n\n\n        \u003cpicture\u003e\n          \u003csource\n            \n              srcset=\"/images/blog/03_hu_40c7fce2fa02cffe.webp\"\n            \n            media=\"(max-width: 575px)\" /\u003e\n          \u003csource\n            \n              srcset=\"/images/blog/03_hu_627f4770fdc523d1.webp\"\n            \n            media=\"(max-width: 767px)\" /\u003e\n          \u003csource\n            \n              srcset=\"/images/blog/03_hu_e9aa2d31267a2ef7.webp\"\n            \n            media=\"(max-width: 991px)\" /\u003e\n          \u003csource\n            \n              srcset=\"/images/blog/03_hu_703b07dc4ab349f7.webp\"\n             /\u003e\n          \u003cimg\n            \n              loading=\"lazy\" decoding=\"async\"\n              src=\"/images/blog/03_hu_a1128046b5493254.jpg\"\n            class=\"  img\"\n            alt=\"\"\n            width=\"1200\"\n            height=\"800\" /\u003e\n        \u003c/picture\u003e\n      \n      \n    \n    \n  \n\n\n  \n\n","permalink":"/blog/post-3/","title":"That which does not kill us makes us stronger"},{"categories":["Nature"],"contents":"Ланцюг — це «м\u0026rsquo;язи» вашого мотоцикла. Брудний, сухий або перетягнутий ланцюг не лише прискорює знос зірок, а й забирає потужність двигуна та може стати причиною серйозної поломки в дорозі.\nПрофесійне обслуговування кожні 500–1000 км (або після кожного дощу) значно подовжить життя вашій трансмісії та збереже ваші кошти на дорогий ремонт.\nЩо входить у послугу? Ми пропонуємо повний цикл догляду за приводом вашого байка:\nПрофесійна мийка системою Kettenmax: Використовуємо спеціальну машинку, яка очищує ланцюг з усіх боків одночасно, не пошкоджуючи сальники (O-ring, X-ring, Z-ring). Безпечне очищення: Як розчинник використовуємо гас (керосин) — він ідеально розчиняє старе мастило та пісок, при цьому залишаючись нейтральним до гумових ущільнювачів. Видалення залишків бруду: Ручне доведення важкодоступних місць та видалення залишків очисника стисненим повітрям або дрантям. Змащування: Нанесення спеціалізованого синтетичного мастила, підібраного під ваш тип ланцюга та умови експлуатації (дорожній байк, ендуро або спорт). Перевірка натягу: Контроль та регулювання провисання ланцюга згідно з мануалом вашого мотоцикла. Чому варто звернутися до нас? Наявність обладнання: Маємо підкати (під задній маятник) для мотоциклів без центральної підніжки (вагою до 350 кг). Якісна хімія: Використовуємо перевірені мастила, які не розлітаються на колесо після виїзду. Швидкість: Процедура займає 20–30 хвилин. Ви можете зачекати на місці. Локація: Зручний заїзд (вказати район, наприклад: Куренівка/Оболонь). Вартість послуг Послуга Ціна Комплекс (чищення + змащування) від 300 грн Регулювання натягу ланцюга від 100 грн Повне ТО приводу (чистка, змазка, натяг) від 400 грн Поради мотоциклісту Коли чистити? Якщо ланки стали жорсткими, з\u0026rsquo;явився сторонній шум або ролики ланцюга блищать «голим» металом. Після процедури: Рекомендуємо дати мастилу «схопитися» (від 15 хвилин до 2 годин), щоб воно не розбризкалося на диск та гуму під час руху. Не мийте мийкою високого тиску! Струмінь води під тиском може пошкодити сальники та вимити заводське мастило зсередини ланок. Як записатися? Працюємо за попередньою домовленістю. Телефонуйте або пишіть у месенджери:\n📞 [Ваш номер телефону] 📍 Адреса: м. Київ, вул. [Назва вулиці], [Номер будинку] 🕒 Графік роботи: [Наприклад: Пн-Сб, 10:00 - 19:00]\nБлок FAQ (Запитання-відповіді) — Чи можна приїхати без центральної підніжки? Так, у нас є спеціальні підкати для безпечного вивішування заднього колеса більшості моделей мотоциклів.\n— Яке мастило ви використовуєте? Ми використовуємо універсальне синтетичне мастило для сальникових ланцюгів. Якщо у вас специфічні вимоги (наприклад, біле мастило або для оффроуду), можемо використати ваше.\n— Скільки часу це займає? В середньому 30 хвилин. Це ідеальний час, щоб перевірити загальний стан зірок та тиск у шинах.\n","date":"October 1, 2021","image":"\n\n\n\n\n\n\n\n\n\n\n\n\n\n\n\n\n\n\n\n\n\n\n\n\n\n\n\n\n  \n\n\n\n\n\n  \n\n  \n  \n    \n      \n    \n\n\n    \n    \n\n\n    \n    \n      \n      \n    \n    \n    \n\n\n    \n    \n      \n      \n        \n\n        \n        \n        \n        \n        \n        \n        \n\n\n        \n        \n\n\n        \u003cpicture\u003e\n          \u003csource\n            \n              srcset=\"/images/blog/01_hu_f7f7d9dadf1a481b.webp\"\n            \n            media=\"(max-width: 575px)\" /\u003e\n          \u003csource\n            \n              srcset=\"/images/blog/01_hu_aeae2a0f05b3ce1a.webp\"\n            \n            media=\"(max-width: 767px)\" /\u003e\n          \u003csource\n            \n              srcset=\"/images/blog/01_hu_a0a0589fe6755c14.webp\"\n            \n            media=\"(max-width: 991px)\" /\u003e\n          \u003csource\n            \n              srcset=\"/images/blog/01_hu_8250f34c936e4042.webp\"\n             /\u003e\n          \u003cimg\n            \n              loading=\"lazy\" decoding=\"async\"\n              src=\"/images/blog/01_hu_1ae9be52500a6f5d.jpg\"\n            class=\"  img\"\n            alt=\"\"\n            width=\"1200\"\n            height=\"800\" /\u003e\n        \u003c/picture\u003e\n      \n      \n    \n    \n  \n\n\n  \n\n","permalink":"/blog/post-1/","title":"Чищення ланцюга"}]